[{"datetime": "2020-01-18", "emotion": "neural", "time": "23:36"}, {"datetime": "2020-01-18", "emotion": "positive", "time": "19:50"}, {"datetime": "2020-01-18", "emotion": "neural", "time": "18:10"}, {"datetime": "2020-01-18", "emotion": "positive", "time": "18:08"}, {"datetime": "2020-01-18", "emotion": "negative", "time": "18:06"}, {"datetime": "2020-01-18", "emotion": "neural", "time": "18:05"}, {"datetime": "2020-01-18", "emotion": "neural", "time": "18:04"}, {"datetime": "2020-01-18", "emotion": "neural", "time": "18:03"}, {"datetime": "2020-01-18", "emotion": "neural", "time": "18:00"}, {"datetime": "2020-01-18", "emotion": "negative", "time": "16:21"}, {"datetime": "2020-01-18", "emotion": "neural", "time": "15:35"}, {"datetime": "2020-01-18", "emotion": "neural", "time": "15:33"}, {"datetime": "2020-01-18", "emotion": "negative", "time": "15:24"}, {"datetime": "2020-01-18", "emotion": "neural", "time": "13:47"}, {"datetime": "2020-01-18", "emotion": "neural", "time": "13:19"}, {"datetime": "2020-01-18", "emotion": "neural", "time": "11:32"}, {"datetime": "2020-01-18", "emotion": "neural", "time": "11:15"}, {"datetime": "2020-01-18", "emotion": "positive", "time": "10:41"}, {"datetime": "2020-01-18", "emotion": "neural", "time": "09:53"}]